pypost/__init__.py
pypost/pypost.py
post_data-4.0.dist-info/METADATA
post_data-4.0.dist-info/WHEEL
post_data-4.0.dist-info/top_level.txt
post_data-4.0.dist-info/RECORD
